prompt_protect/__init__.py
prompt_protect/prompt_protect.py
prompt_protect-0.1.dist-info/METADATA
prompt_protect-0.1.dist-info/WHEEL
prompt_protect-0.1.dist-info/RECORD
