Metadata-Version: 2.1
Name: prompt-protect
Version: 0.1
Summary: An NLP classification for detecting prompt injection
Home-page: https://github.com/thevgergroup/prompt_protect
License: MIT
Keywords: AI,GenAI,security,prompt injection,detection,classification,NLP
Author: patrick o'leary
Author-email: pjaol@pjaol.com
Requires-Python: >=3.9,<4.0
Classifier: License :: OSI Approved :: MIT License
Classifier: Programming Language :: Python :: 3
Classifier: Programming Language :: Python :: 3.9
Classifier: Programming Language :: Python :: 3.10
Classifier: Programming Language :: Python :: 3.11
Classifier: Programming Language :: Python :: 3.12
Classifier: Topic :: Scientific/Engineering :: Artificial Intelligence
Classifier: Topic :: Security
Requires-Dist: datasets (>=2.21.0,<3.0.0)
Requires-Dist: numpy (==1.26.4)
Requires-Dist: pandas (>=2.2.2,<3.0.0)
Requires-Dist: scikit-learn (>=1.5.1,<2.0.0)
Requires-Dist: skops (>=0.10.0,<0.11.0)
Requires-Dist: torch (==2.2.2)
Requires-Dist: transformers (>=4.44.2,<5.0.0)
Project-URL: Repository, https://github.com/thevgergroup/prompt_protect.git
